quantier/__init__.py
quantier/quantier.py
qiskit_han-0.6.0.dist-info/METADATA
qiskit_han-0.6.0.dist-info/WHEEL
qiskit_han-0.6.0.dist-info/top_level.txt
qiskit_han-0.6.0.dist-info/RECORD
