Metadata-Version: 2.1
Name: qiskit-han
Version: 0.6.0
Summary: A quantum provider for Qiskit
Classifier: Programming Language :: Python :: 3
Classifier: License :: OSI Approved :: MIT License
Classifier: Operating System :: OS Independent
Requires-Python: >=3.6
Requires-Dist: qiskit
Requires-Dist: qiskit-aermysql-connector-python
